flask_dingding/__init__.py
flask_dingding/main.py
flask_dingding-0.0.1.dist-info/LICENSE
flask_dingding-0.0.1.dist-info/METADATA
flask_dingding-0.0.1.dist-info/WHEEL
flask_dingding-0.0.1.dist-info/top_level.txt
flask_dingding-0.0.1.dist-info/RECORD
